ddquint/__init__.py
ddquint/main.py
ddquint/config/__init__.py
ddquint/config/config.py
ddquint/config/config_display.py
ddquint/config/exceptions.py
ddquint/config/logging_config.py
ddquint/config/template_generator.py
ddquint/core/__init__.py
ddquint/core/clustering.py
ddquint/core/copy_number.py
ddquint/core/file_processor.py
ddquint/core/list_report.py
ddquint/utils/__init__.py
ddquint/utils/file_io.py
ddquint/utils/gui.py
ddquint/utils/parameter_editor.py
ddquint/utils/template_creator.py
ddquint/utils/template_parser.py
ddquint/utils/well_utils.py
ddquint/visualization/__init__.py
ddquint/visualization/plate_plots.py
ddquint/visualization/well_plots.py
ddquint-0.1.0.dist-info/licenses/LICENSE
ddquint-0.1.0.dist-info/METADATA
ddquint-0.1.0.dist-info/WHEEL
ddquint-0.1.0.dist-info/entry_points.txt
ddquint-0.1.0.dist-info/top_level.txt
ddquint-0.1.0.dist-info/RECORD
