Metadata-Version: 2.4
Name: ddquint
Version: 0.1.0
Summary: Droplet Digital PCR Multiplex Analysis for chromosomal copy number detection
Author-email: Jakob Wimmer <globuds133@gmail.com>
License: MIT
Project-URL: Homepage, https://github.com/globuzzz2000/ddQuint
Project-URL: Documentation, https://github.com/globuzzz2000/ddQuint#readme
Project-URL: Bug Tracker, https://github.com/globuzzz2000/ddQuint/issues
Classifier: Development Status :: 4 - Beta
Classifier: Intended Audience :: Science/Research
Classifier: Topic :: Scientific/Engineering :: Bio-Informatics
Classifier: Programming Language :: Python :: 3
Classifier: Programming Language :: Python :: 3.10
Classifier: Programming Language :: Python :: 3 :: Only
Classifier: Programming Language :: Python :: 3.11
Classifier: Programming Language :: Python :: 3.12
Requires-Python: >=3.10
License-File: LICENSE
Requires-Dist: pandas>=1.0.0
Requires-Dist: numpy>=1.18.0
Requires-Dist: matplotlib>=3.3.0
Requires-Dist: scikit-learn>=0.24.0
Requires-Dist: hdbscan>=0.8.27
Requires-Dist: openpyxl>=3.0.5
Requires-Dist: wxpython>=4.1.0
Requires-Dist: colorama>=0.4.4
Requires-Dist: tqdm>=4.60.0
Requires-Dist: pyobjc-core; platform_system == "Darwin"
Requires-Dist: pyobjc-framework-Cocoa; platform_system == "Darwin"
Provides-Extra: dev
Requires-Dist: pytest>=7.0.0; extra == "dev"
Requires-Dist: pytest-cov>=4.0.0; extra == "dev"
Requires-Dist: black>=20.8b1; extra == "dev"
Provides-Extra: test
Requires-Dist: pytest>=7.0.0; extra == "test"
Requires-Dist: pytest-cov>=4.0.0; extra == "test"
Dynamic: license-file
